ZathuraProject/__init__.py
ZathuraProject/bugtracker.py
ZathuraProject/fetcher.py
ZathuraProject/sqlite_definition.py
ZathuraProject/utility.py
ZathuraProject/zathura.py
ZathuraProject/zathuraseption.py
zathura-0.0.6.0b1.dist-info/LICENSE.txt
zathura-0.0.6.0b1.dist-info/METADATA
zathura-0.0.6.0b1.dist-info/WHEEL
zathura-0.0.6.0b1.dist-info/entry_points.txt
zathura-0.0.6.0b1.dist-info/top_level.txt
zathura-0.0.6.0b1.dist-info/RECORD
