Metadata-Version: 2.1
Name: zathura
Version: 0.0.6.0b1
Summary: Zathura is a small space logger. It logs stuff into her logbook as she drifts into vast unknown of development phase.
Home-page: https://github.com/p1r-a-t3/zathura
Author: Mr Anderson
Author-email: ibtehaz.92@gmail.com
License: MIT
Platform: UNKNOWN
Classifier: Programming Language :: Python :: 3
Classifier: License :: OSI Approved :: MIT License
Classifier: Operating System :: OS Independent
Requires-Dist: peewee
Requires-Dist: pyfiglet
